{
  "name": "airbob-outbox-connector",
  "config": {
    "connector.class": "io.debezium.connector.mysql.MySqlConnector",
    "tasks.max": "1",
    "database.hostname": "mysql",
    "database.port": "3306",
    "database.user": "root",
    "database.password": "root",
    "database.server.id": "184054",
    "database.server.name": "airbob_server",
    "database.include.list": "airbobdb",
    "table.include.list": "airbobdb.outbox",
    "database.history.kafka.bootstrap.servers": "kafka:9092",
    "database.history.kafka.topic": "schema-changes.inventory",
    "topic.prefix": "outbox.events",
    "transforms": "outbox",
    "transforms.outbox.type": "io.debezium.transforms.outbox.EventRouter",
    "transforms.outbox.table.field.event.key": "aggregateId",
    "transforms.outbox.table.field.event.payload": "payload",
    "transforms.outbox.route.by.field": "aggregateType",
    "transforms.outbox.route.topic.replacement": "${routedByValue}.events"
  }
}
